setup.cfg
setup.py
recommendy/__init__.py
recommendy/data_handler.py
recommendy/exceptions.py
recommendy/json_data_handler.py
recommendy/recommender.py
recommendy/similarity_metric.py
recommendy/xml_data_handler.py
recommendy.egg-info/PKG-INFO
recommendy.egg-info/SOURCES.txt
recommendy.egg-info/dependency_links.txt
recommendy.egg-info/entry_points.txt
recommendy.egg-info/pbr.json
recommendy.egg-info/requires.txt
recommendy.egg-info/top_level.txt