Metadata-Version: 1.1
Name: recommendy
Version: 0.0.2
Summary: Python3 recommendation system
Home-page: https://github.com/d0ivanov/recommendy
Author: Dobromir Ivanov
Author-email: dobromir0ivanov@gmail.com
License: MIT
Keywords: recommendation
Platform: UNKNOWN
Classifier: Intended Audience :: Developers
Classifier: Topic :: Internet :: WWW/HTTP :: Indexing/Search
Classifier: License :: OSI Approved :: MIT License
Classifier: Programming Language :: Python :: 3
Classifier: Programming Language :: Python :: 3.4
